{
    "@context": [
        "http://iiif.io/api/presentation/2/context.json",
        "http://codh.rois.ac.jp/iiif/curation/1/context.json"
    ],
    "@id": "https://kunshujo.dl.itc.u-tokyo.ac.jp/data/curation/16-A00-6010-8-57.json",
    "@type": "cr:Curation",
    "label": "〔入寮願書書式摺物〕",
    "selections": [
        {
            "@id": "https://kunshujo.dl.itc.u-tokyo.ac.jp/data/curation/16-A00-6010-8-57.json/range1",
            "@type": "sc:Range",
            "label": "Manual curation by IIIF Curation Viewer",
            "members": [
                {
                    "@id": "https://iiif.dl.itc.u-tokyo.ac.jp/repo/iiif/25234/canvas/p20#xywh=2015,495,1626,4274",
                    "@type": "sc:Canvas",
                    "description": "<dl class=\"row\"><dt class=\"col-sm-3\">地名</dt><dd class=\"col-sm-9\">大阪</dd><dt class=\"col-sm-3\">書誌事項</dt><dd class=\"col-sm-9\">26.0×10.0　大阪舎密局のものか？</dd><dt class=\"col-sm-3\">タイトル</dt><dd class=\"col-sm-9\">〔入寮願書書式摺物〕</dd><dt class=\"col-sm-3\">和暦</dt><dd class=\"col-sm-9\">明治2?年</dd><dt class=\"col-sm-3\">数量</dt><dd class=\"col-sm-9\">１枚</dd><dt class=\"col-sm-3\">版種類</dt><dd class=\"col-sm-9\">木版</dd><dt class=\"col-sm-3\">西暦コード</dt><dd class=\"col-sm-9\">18690199099</dd></dl>",
                    "label": "16-A00-6010-8-57",
                    "metadata": [
                        {
                            "label": "地名",
                            "value": "大阪"
                        },
                        {
                            "label": "書誌事項",
                            "value": "26.0×10.0　大阪舎密局のものか？"
                        },
                        {
                            "label": "タイトル",
                            "value": "〔入寮願書書式摺物〕"
                        },
                        {
                            "label": "和暦",
                            "value": "明治2?年"
                        },
                        {
                            "label": "数量",
                            "value": "１枚"
                        },
                        {
                            "label": "版種類",
                            "value": "木版"
                        },
                        {
                            "label": "西暦コード",
                            "value": 18690199099
                        }
                    ],
                    "thumbnail": "https://iiif.dl.itc.u-tokyo.ac.jp/repo/iiif-img/154573/2015,495,1626,4274/,300/0/default.jpg"
                }
            ],
            "within": {
                "@id": "https://iiif.dl.itc.u-tokyo.ac.jp/repo/iiif/25234/manifest",
                "@label": "捃拾帖 八",
                "@type": "sc:Manifest"
            }
        }
    ]
}