{
    "@context": [
        "http://iiif.io/api/presentation/2/context.json",
        "http://codh.rois.ac.jp/iiif/curation/1/context.json"
    ],
    "@id": "https://kunshujo.dl.itc.u-tokyo.ac.jp/data/curation/16-A00-6010-9-27.json",
    "@type": "cr:Curation",
    "label": "Curating list",
    "selections": [
        {
            "@id": "https://kunshujo.dl.itc.u-tokyo.ac.jp/data/curation/16-A00-6010-9-27.json/range1",
            "@type": "sc:Range",
            "label": "Manual curation by IIIF Curation Viewer",
            "members": [
                {
                    "@id": "https://iiif.dl.itc.u-tokyo.ac.jp/repo/iiif/25197/canvas/p7#xywh=883,2310,1852,2564",
                    "@type": "sc:Canvas",
                    "label": "16-A00-6010-9-27",
                    "metadata": [
                        {
                            "label": "西暦コード",
                            "value": 18320099099
                        },
                        {
                            "label": "数量",
                            "value": "１枚"
                        },
                        {
                            "label": "版種類",
                            "value": "木版"
                        },
                        {
                            "label": "地名",
                            "value": "京都"
                        },
                        {
                            "label": "タイトル",
                            "value": "書状独稽古引札"
                        },
                        {
                            "label": "和暦",
                            "value": "天保3年"
                        },
                        {
                            "label": "書誌事項",
                            "value": "15.3×11.0　龍章堂閑斎筆、京都書肆合梓"
                        },
                        {
                            "label": "形態分類",
                            "value": "引札"
                        }
                    ]
                }
            ],
            "within": {
                "@id": "https://iiif.dl.itc.u-tokyo.ac.jp/repo/iiif/25197/manifest",
                "@label": "捃拾帖 九",
                "@type": "sc:Manifest"
            }
        }
    ]
}