{"@context": ["http://iiif.io/api/presentation/2/context.json","http://codh.rois.ac.jp/iiif/curation/1/context.json"],"@id": "https://kunshujo.dl.itc.u-tokyo.ac.jp/data/curation/16-A00-6010-14-6.json","@type": "cr:Curation","label": "〔築地電信局送信料受領書〕（『捃拾帖』第14帖のうち）","selections": [{"@id": "https://kunshujo.dl.itc.u-tokyo.ac.jp/data/curation/16-A00-6010-14-6.json/range1","@type": "sc:Range","label": "Manual curation by IIIF Curation Viewer","members": [{"@id": "https://iiif.dl.itc.u-tokyo.ac.jp/repo/iiif/d31a5d15-afe1-411d-abaa-ed9263d5c800/canvas/p5#xywh=880,518,5631,5331","@type": "sc:Canvas","description": "<table class=\"table\"><tr><th>和暦</th><td>明治5?年</td></tr><tr><th>西暦コード</th><td>18720199099</td></tr><tr><th>タイトル</th><td>〔築地電信局送信料受領書〕</td></tr><tr><th>版種類</th><td>木版</td></tr><tr><th>数量</th><td>１枚</td></tr><tr><th>書誌事項</th><td>24.6×8.5　３４銭半、大坂行、３５字、摺物に書込形式</td></tr><tr><th>内容分類</th><td>諸営業</td></tr><tr><th>帖数</th><td><a href='https://iiif.dl.itc.u-tokyo.ac.jp/repo/s/tanaka/document/d31a5d15-afe1-411d-abaa-ed9263d5c800#?cv=4'>『捃拾帖』第14帖</a></td></tr><tr><th>地名</th><td>東京</td></tr></table>","label": "16-A00-6010-14-6","metadata": [{"label": "和暦","value": "明治5?年"},{"label": "西暦コード","value": 18720199099},{"label": "タイトル","value": "〔築地電信局送信料受領書〕"},{"label": "版種類","value": "木版"},{"label": "数量","value": "１枚"},{"label": "書誌事項","value": "24.6×8.5　３４銭半、大坂行、３５字、摺物に書込形式"},{"label": "内容分類","value": "諸営業"},{"label": "帖数","value": "『捃拾帖』第14帖"},{"label": "地名","value": "東京"}],"thumbnail": "https://iiif.dl.itc.u-tokyo.ac.jp/iiif/kunshujou/A00_6010/014/014_0005.tif/880,518,5631,5331/,300/0/default.jpg"}],"within": {"@id": "https://iiif.dl.itc.u-tokyo.ac.jp/repo/iiif/d31a5d15-afe1-411d-abaa-ed9263d5c800/manifest","@label": "捃拾帖 十四","@type": "sc:Manifest"}}]}