{
    "@context": [
        "http://iiif.io/api/presentation/2/context.json",
        "http://codh.rois.ac.jp/iiif/curation/1/context.json"
    ],
    "@id": "https://kunshujo.dl.itc.u-tokyo.ac.jp/data/curation/16-A00-6010-15-42.json",
    "@type": "cr:Curation",
    "label": "幾那保全酒引札",
    "selections": [
        {
            "@id": "https://kunshujo.dl.itc.u-tokyo.ac.jp/data/curation/16-A00-6010-15-42.json/range1",
            "@type": "sc:Range",
            "label": "Manual curation by IIIF Curation Viewer",
            "members": [
                {
                    "@id": "https://iiif.dl.itc.u-tokyo.ac.jp/repo/iiif/25203/canvas/p21#xywh=3758,583,2753,1990",
                    "@type": "sc:Canvas",
                    "description": "<table class=\"table\"><tr><th>和暦</th><td>明治9年</td></tr><tr><th>数量</th><td>２枚</td></tr><tr><th>版種類</th><td>銅版</td></tr><tr><th>地名</th><td>東京</td></tr><tr><th>西暦コード</th><td>18760099099</td></tr><tr><th>形態分類</th><td>引札</td></tr><tr><th>内容分類</th><td>病気・医療</td></tr><tr><th>タイトル</th><td>幾那保全酒引札</td></tr><tr><th>書誌事項</th><td>8.3×10.0と12.0×8.8　神田雉子町保全堂製、AROMATIC FINE BITTER、１枚は効能書</td></tr></table>",
                    "label": "16-A00-6010-15-42",
                    "metadata": [
                        {
                            "label": "和暦",
                            "value": "明治9年"
                        },
                        {
                            "label": "数量",
                            "value": "２枚"
                        },
                        {
                            "label": "版種類",
                            "value": "銅版"
                        },
                        {
                            "label": "地名",
                            "value": "東京"
                        },
                        {
                            "label": "西暦コード",
                            "value": 18760099099
                        },
                        {
                            "label": "形態分類",
                            "value": "引札"
                        },
                        {
                            "label": "内容分類",
                            "value": "病気・医療"
                        },
                        {
                            "label": "タイトル",
                            "value": "幾那保全酒引札"
                        },
                        {
                            "label": "書誌事項",
                            "value": "8.3×10.0と12.0×8.8　神田雉子町保全堂製、AROMATIC FINE BITTER、１枚は効能書"
                        }
                    ],
                    "thumbnail": "https://iiif.dl.itc.u-tokyo.ac.jp/repo/iiif-img/154951/3758,583,2753,1990/,300/0/default.jpg"
                }
            ],
            "within": {
                "@id": "https://iiif.dl.itc.u-tokyo.ac.jp/repo/iiif/25203/manifest",
                "@label": "捃拾帖 十五",
                "@type": "sc:Manifest"
            }
        }
    ]
}