{
    "@context": [
        "http://iiif.io/api/presentation/2/context.json",
        "http://codh.rois.ac.jp/iiif/curation/1/context.json"
    ],
    "@id": "https://kunshujo.dl.itc.u-tokyo.ac.jp/data/curation/16-A00-6010-15-113.json",
    "@type": "cr:Curation",
    "label": "〔スグリジヤム　ラベル〕",
    "selections": [
        {
            "@id": "https://kunshujo.dl.itc.u-tokyo.ac.jp/data/curation/16-A00-6010-15-113.json/range1",
            "@type": "sc:Range",
            "label": "Manual curation by IIIF Curation Viewer",
            "members": [
                {
                    "@id": "https://iiif.dl.itc.u-tokyo.ac.jp/repo/iiif/25203/canvas/p50#xywh=3712,544,2792,1329",
                    "@type": "sc:Canvas",
                    "description": "<table class=\"table\"><tr><th>和暦</th><td>明治10年</td></tr><tr><th>数量</th><td>１枚</td></tr><tr><th>版種類</th><td>木版</td></tr><tr><th>地名</th><td>東京</td></tr><tr><th>西暦コード</th><td>18770099099</td></tr><tr><th>タイトル</th><td>〔スグリジヤム　ラベル〕</td></tr><tr><th>書誌事項</th><td>8.2×16.5　彩色、東京四谷内藤新宿勧農局試験場製</td></tr></table>",
                    "label": "16-A00-6010-15-113",
                    "metadata": [
                        {
                            "label": "和暦",
                            "value": "明治10年"
                        },
                        {
                            "label": "数量",
                            "value": "１枚"
                        },
                        {
                            "label": "版種類",
                            "value": "木版"
                        },
                        {
                            "label": "地名",
                            "value": "東京"
                        },
                        {
                            "label": "西暦コード",
                            "value": 18770099099
                        },
                        {
                            "label": "タイトル",
                            "value": "〔スグリジヤム　ラベル〕"
                        },
                        {
                            "label": "書誌事項",
                            "value": "8.2×16.5　彩色、東京四谷内藤新宿勧農局試験場製"
                        }
                    ],
                    "thumbnail": "https://iiif.dl.itc.u-tokyo.ac.jp/repo/iiif-img/154980/3712,544,2792,1329/,300/0/default.jpg"
                }
            ],
            "within": {
                "@id": "https://iiif.dl.itc.u-tokyo.ac.jp/repo/iiif/25203/manifest",
                "@label": "捃拾帖 十五",
                "@type": "sc:Manifest"
            }
        }
    ]
}