{
    "@context": [
        "http://iiif.io/api/presentation/2/context.json",
        "http://codh.rois.ac.jp/iiif/curation/1/context.json"
    ],
    "@id": "https://utda.github.io/text/json/16-A00-6010-7-18.json",
    "@type": "cr:Curation",
    "label": "Curating list",
    "selections": [
        {
            "@id": "https://utda.github.io/text/json/16-A00-6010-7-18.json/range1",
            "@type": "sc:Range",
            "label": "Manual curation by IIIF Curation Viewer",
            "members": [
                {
                    "@id": "https://iiif.dl.itc.u-tokyo.ac.jp/repo/iiif/25258/canvas/p11#xywh=1025,653,2429,3745",
                    "@type": "sc:Canvas",
                    "label": "16-A00-6010-7-18",
                    "metadata": [
                        {
                            "label": "書誌事項",
                            "value": "14.5×22.5　「やつこぶし・茶ぶし・梅見さん御はみがき・新作つぢうらいり」とあり、芝神明前浅野定右衛門、宣伝のため「生人形」御覧に入れるとあり"
                        },
                        {
                            "label": "形態分類",
                            "value": "Ｗ"
                        },
                        {
                            "label": "西暦コード",
                            "value": "18620199099"
                        },
                        {
                            "label": "タイトル",
                            "value": "薬はみがき梅見散引札"
                        },
                        {
                            "label": "数量",
                            "value": "１枚"
                        },
                        {
                            "label": "内容分類",
                            "value": "7"
                        },
                        {
                            "label": "年号",
                            "value": "文久２？"
                        },
                        {
                            "label": "所蔵機関（名称）",
                            "value": "東京大学総合図書館-A00-6010-7-18"
                        },
                        {
                            "label": "地名",
                            "value": "江戸"
                        },
                        {
                            "label": "和暦",
                            "value": "文久2?年"
                        },
                        {
                            "label": "版種類",
                            "value": "木版"
                        }
                    ]
                }
            ],
            "within": {
                "@id": "https://iiif.dl.itc.u-tokyo.ac.jp/repo/iiif/25258/manifest",
                "@label": "捃拾帖 七",
                "@type": "sc:Manifest"
            }
        }
    ]
}